{
  "groups": [
    {
      "title": "Default Content",
      "id": "default",
      "components": [
        {
          "title": "Text",
          "id": "text",
          "plugins": {
            "xwalk": {
              "page": {
                "resourceType": "core/franklin/components/text/v1/text",
                "template": {}
              }
            }
          }
        },
        {
          "title": "Title",
          "id": "title",
          "plugins": {
            "xwalk": {
              "page": {
                "resourceType": "core/franklin/components/title/v1/title",
                "template": {
                  "model": "title"
                }
              }
            }
          }
        },
        {
          "title": "Image",
          "id": "image",
          "plugins": {
            "xwalk": {
              "page": {
                "resourceType": "core/franklin/components/image/v1/image",
                "template": {
                  "image": "",
                  "imageAlt": ""
                }
              }
            }
          }
        },
        {
          "title": "Button",
          "id": "button",
          "plugins": {
            "xwalk": {
              "page": {
                "resourceType": "core/franklin/components/button/v1/button",
                "template": {
                  "model": "button"
                }
              }
            }
          }
        }
      ]
    },
    {
      "title": "Sections",
      "id": "sections",
      "components": [
        {
          "title": "Section",
          "id": "section",
          "plugins": {
            "xwalk": {
              "page": {
                "resourceType": "core/franklin/components/section/v1/section",
                "template": {
                  "model": "section"
                }
              }
            }
          }
        }
      ]
    },
    {
      "title": "Blocks",
      "id": "blocks",
      "components": [
        {
          "title": "Stats",
          "id": "stats",
          "plugins": {
            "xwalk": {
              "page": {
                "resourceType": "core/franklin/components/block/v1/block",
                "template": {
                  "name": "Stats",
                  "filter": "stats"
                }
              }
            }
          }
        },
        {
          "title": "Stats Item",
          "id": "stats-item",
          "plugins": {
            "xwalk": {
              "page": {
                "resourceType": "core/franklin/components/block/v1/block/item",
                "template": {
                  "name": "Stats Item",
                  "model": "stats-item",
                  "value": "",
                  "label": ""
                }
              }
            }
          }
        },
        {
          "title": "Accordion",
          "id": "accordion",
          "plugins": {
            "xwalk": {
              "page": {
                "resourceType": "core/franklin/components/block/v1/block",
                "template": {
                  "name": "Accordion",
                  "filter": "accordion"
                }
              }
            }
          }
        },
        {
          "title": "Accordion Item",
          "id": "accordion-item",
          "plugins": {
            "xwalk": {
              "page": {
                "resourceType": "core/franklin/components/block/v1/block/item",
                "template": {
                  "name": "Accordion Item",
                  "model": "accordion-item",
                  "title": "",
                  "description": ""
                }
              }
            }
          }
        },
        {
          "title": "Cards",
          "id": "cards",
          "plugins": {
            "xwalk": {
              "page": {
                "resourceType": "core/franklin/components/block/v1/block",
                "template": {
                  "name": "Cards",
                  "filter": "cards"
                }
              }
            }
          }
        },
        {
          "title": "Card",
          "id": "card",
          "plugins": {
            "xwalk": {
              "page": {
                "resourceType": "core/franklin/components/block/v1/block/item",
                "template": {
                  "name": "Card",
                  "model": "card",
                  "image": "",
                  "imageAlt": "",
                  "text": ""
                }
              }
            }
          }
        },
        {
          "title": "Columns",
          "id": "columns",
          "plugins": {
            "xwalk": {
              "page": {
                "resourceType": "core/franklin/components/columns/v1/columns",
                "template": {
                  "columns": "2",
                  "rows": "1"
                }
              }
            }
          }
        },
        {
          "title": "Countries",
          "id": "countries",
          "plugins": {
            "xwalk": {
              "page": {
                "resourceType": "core/franklin/components/block/v1/block",
                "template": {
                  "name": "Countries",
                  "model": "countries",
                  "filter": "countries"
                }
              }
            }
          }
        },
        {
          "title": "Countries Item",
          "id": "countries-item",
          "plugins": {
            "xwalk": {
              "page": {
                "resourceType": "core/franklin/components/block/v1/block/item",
                "template": {
                  "name": "Countries Item",
                  "model": "countries-item"
                }
              }
            }
          }
        },
        {
          "title": "Fragment",
          "id": "fragment",
          "plugins": {
            "xwalk": {
              "page": {
                "resourceType": "core/franklin/components/block/v1/block",
                "template": {
                  "name": "Fragment",
                  "model": "fragment"
                }
              }
            }
          }
        },
        {
          "title": "Hero",
          "id": "hero",
          "plugins": {
            "xwalk": {
              "page": {
                "resourceType": "core/franklin/components/block/v1/block",
                "template": {
                  "name": "Hero",
                  "model": "hero",
                  "image": "",
                  "imageAlt": "",
                  "video": "",
                  "text": ""
                }
              }
            }
          }
        },
        {
          "title": "Spotlight",
          "id": "spotlight",
          "plugins": {
            "xwalk": {
              "page": {
                "resourceType": "core/franklin/components/block/v1/block",
                "template": {
                  "name": "Spotlight",
                  "filter": "spotlight"
                }
              }
            }
          }
        },
        {
          "title": "Spotlight Item",
          "id": "spotlight-item",
          "plugins": {
            "xwalk": {
              "page": {
                "resourceType": "core/franklin/components/block/v1/block/item",
                "template": {
                  "name": "Spotlight Item",
                  "model": "spotlight-item",
                  "image": "",
                  "imageAlt": "",
                  "videoUrl": "",
                  "text": ""
                }
              }
            }
          }
        },
        {
          "title": "Subscribe",
          "id": "subscribe",
          "plugins": {
            "xwalk": {
              "page": {
                "resourceType": "core/franklin/components/block/v1/block",
                "template": {
                  "name": "Subscribe",
                  "model": "subscribe",
                  "filter": "subscribe",
                  "backgroundImage": "",
                  "title": "",
                  "description": ""
                }
              }
            }
          }
        },
        {
          "title": "Subscribe Item",
          "id": "subscribe-item",
          "plugins": {
            "xwalk": {
              "page": {
                "resourceType": "core/franklin/components/block/v1/block/item",
                "template": {
                  "name": "Subscribe Item",
                  "model": "subscribe-item",
                  "title": "",
                  "description": ""
                }
              }
            }
          }
        },
        {
          "title": "Tabs",
          "id": "tabs",
          "plugins": {
            "xwalk": {
              "page": {
                "resourceType": "core/franklin/components/block/v1/block",
                "template": {
                  "name": "Tabs",
                  "filter": "tabs"
                }
              }
            }
          }
        },
        {
          "title": "Tab",
          "id": "tab-item",
          "plugins": {
            "xwalk": {
              "page": {
                "resourceType": "core/franklin/components/block/v1/block/item",
                "template": {
                  "name": "Tab",
                  "model": "tab-item",
                  "image": "",
                  "imageAlt": "",
                  "text": ""
                }
              }
            }
          }
        },
        {
          "title": "Youtube",
          "id": "youtube",
          "plugins": {
            "xwalk": {
              "page": {
                "resourceType": "core/franklin/components/block/v1/block",
                "template": {
                  "name": "Youtube",
                  "model": "youtube"
                }
              }
            }
          }
        }
      ]
    }
  ]
}